vtb_py_logging/__about__.py
vtb_py_logging/__init__.py
vtb_py_logging/aiohttp.py
vtb_py_logging/aiomq.py
vtb_py_logging/configure.py
vtb_py_logging/django.py
vtb_py_logging/fastapi.py
vtb_py_logging/filters.py
vtb_py_logging/formatters.py
vtb_py_logging/log_config.py
vtb_py_logging/log_extra.py
vtb_py_logging/logbook_configure.py
vtb_py_logging/pretty.py
vtb_py_logging/request_id.py
vtb_py_logging/test_logging.py
vtb_py_logging/utils.py
vtb_py_logging-1.1.18.dist-info/METADATA
vtb_py_logging-1.1.18.dist-info/WHEEL
vtb_py_logging-1.1.18.dist-info/top_level.txt
vtb_py_logging-1.1.18.dist-info/RECORD
