Metadata-Version: 2.1
Name: vtb-py-logging
Version: 1.1.18
Summary: test
Home-page: UNKNOWN
Author: Vladislav Steshenko
Author-email: vsteshenko@vtb.ru
License: UNKNOWN
Platform: UNKNOWN
Requires-Dist: orjson
Requires-Dist: python-multipart
